AUTHORS.rst
CONTRIBUTING.rst
HISTORY.rst
LICENSE
MANIFEST.in
README.rst
setup.cfg
setup.py
superscription/__init__.py
superscription/superscription.py
superscription.egg-info/PKG-INFO
superscription.egg-info/SOURCES.txt
superscription.egg-info/dependency_links.txt
superscription.egg-info/not-zip-safe
superscription.egg-info/requires.txt
superscription.egg-info/top_level.txt