Metadata-Version: 1.1
Name: superscription
Version: 0.1.2
Summary: Superscriptions: A (super-)thin Python 2.7 wrapper around the Superfeedr PubSubHubbub API.
Home-page: https://github.com/shrikant-joshi/superscription
Author: Shrikant Joshi
Author-email: shrikant.j@gmail.com
License: BSD
Keywords: superscription
Platform: UNKNOWN
Classifier: Development Status :: 4 - Beta
Classifier: Intended Audience :: Developers
Classifier: License :: OSI Approved :: BSD License
Classifier: Natural Language :: English
Classifier: Programming Language :: Python :: 2
Classifier: Programming Language :: Python :: 2.6
Classifier: Programming Language :: Python :: 2.7
